hydro_deploy-0.5.0.dist-info/METADATA
hydro_deploy-0.5.0.dist-info/WHEEL
hydro_deploy-0.5.0.dist-info/entry_points.txt
hydro/.gitignore
hydro/async_wrapper.py
hydro/cli.py
hydro/_core.pyi
hydro/__init__.py
hydro/_core.pyd
hydro_deploy-0.5.0.dist-info/RECORD
