Metadata-Version: 2.1
Name: hydro-deploy
Version: 0.5.0
Summary: A toolkit for deploying Hydro services to cloud platforms.
License: Apache-2.0
Requires-Python: >=3.7
